simple_minimizer/__init__.py
simple_minimizer/logistic_constraints.py
simple_minimizer/minimizer.py
simple_minimizer/vertex.py
simple_minimizer-2.0.0.dist-info/METADATA
simple_minimizer-2.0.0.dist-info/WHEEL
simple_minimizer-2.0.0.dist-info/licenses/LICENSE
simple_minimizer-2.0.0.dist-info/RECORD
