Metadata-Version: 2.1
Name: simple-minimizer
Version: 2.0.0
Summary: A brutally simple, extremely robust minimizer
Project-URL: Homepage, https://github.com/tjradcliffe/simple-minimizer
Project-URL: Bug Tracker, https://github.com/tjradcliffe/simple-minimizer/issues
Author-email: TJ Radcliffe <tj@tjradcliffe.com>
License: Copyright (c) 2022 Thomas J. Radcliffe
License-File: LICENSE
Classifier: License :: OSI Approved :: MIT License
Classifier: Operating System :: OS Independent
Classifier: Programming Language :: Python :: 3
Requires-Python: >=3.6
